<?xml version="1.0" encoding="utf-8" ?>
<dwsync>
<file name="fontawesome-webfont78ce.eot" server="ftp.hmdcubes.com//padmacatering/" local="130982738700000000" remote="131210060400000000" Dst="0" />
<file name="fontawesome-webfont78ce.woff" server="ftp.hmdcubes.com//padmacatering/" local="130982738710000000" remote="131210060400000000" Dst="0" />
<file name="fontawesome-webfont78ce.ttf" server="ftp.hmdcubes.com//padmacatering/" local="130982738710000000" remote="131210060400000000" Dst="0" />
<file name="fontawesome-webfont78ce.svg" server="ftp.hmdcubes.com//padmacatering/" local="130982738710000000" remote="131210060400000000" Dst="0" />
<file name="fontawesome-webfontd41d.eot" server="ftp.hmdcubes.com//padmacatering/" local="130982738700000000" remote="131210060400000000" Dst="0" />
<file name="fontawesome-webfont78ce.eot" server="ftp.padmacatering.com//padmacatering/" local="130982738700000000" remote="131636288400000000" Dst="0" />
<file name="fontawesome-webfont78ce.ttf" server="ftp.padmacatering.com//padmacatering/" local="130982738710000000" remote="131636288400000000" Dst="0" />
<file name="fontawesome-webfont78ce.woff" server="ftp.padmacatering.com//padmacatering/" local="130982738710000000" remote="131636288400000000" Dst="0" />
<file name="fontawesome-webfont78ce.svg" server="ftp.padmacatering.com//padmacatering/" local="130982738710000000" remote="131636288400000000" Dst="0" />
<file name="fontawesome-webfontd41d.eot" server="ftp.padmacatering.com//padmacatering/" local="130982738700000000" remote="131636288400000000" Dst="0" />
</dwsync>